CHANGES
COPYRIGHT
MANIFEST.in
Makefile
README
index.cgi
setup.cfg
setup.py
twanager
wsgiapp.py
docs/Makefile
docs/conf.py
docs/index.rst
docs/tiddlyweb.commands.rst
docs/tiddlyweb.filters.rst
docs/tiddlyweb.model.rst
docs/tiddlyweb.rst
docs/tiddlyweb.serializations.rst
docs/tiddlyweb.stores.rst
docs/tiddlyweb.web.challengers.rst
docs/tiddlyweb.web.extractors.rst
docs/tiddlyweb.web.handler.rst
docs/tiddlyweb.web.rst
docs/tiddlyweb.wikitext.rst
test/SCHEDULE
test/__init__.py
test/fixtures.py
test/http_runner.py
test/httptest.yaml
test/indexer.py
test/peermore.png
test/simpleplugin.py
test/test_bag.py
test/test_bag_filtering.py
test/test_collection_tiddlers.py
test/test_commands.py
test/test_control.py
test/test_external_load.py
test/test_filter.py
test/test_filtered_recipes.py
test/test_json_perms.py
test/test_limit_filter.py
test/test_make_cookie.py
test/test_merge_config.py
test/test_muchdata.py
test/test_parse_filter_query.py
test/test_policy.py
test/test_query.py
test/test_query_extract.py
test/test_recipe.py
test/test_recipe_template.py
test/test_render_wikitext.py
test/test_roundtrip.py
test/test_select_filter.py
test/test_serialize_bag.py
test/test_serialize_recipe.py
test/test_serialize_tiddler.py
test/test_serializer.py
test/test_sort_filter.py
test/test_specialbag.py
test/test_store.py
test/test_store_bag.py
test/test_store_hooks.py
test/test_store_recipe.py
test/test_store_search.py
test/test_store_tiddler.py
test/test_store_user.py
test/test_text_filter.py
test/test_text_store_fields.py
test/test_tiddler.py
test/test_tiddler_fields_as_strings.py
test/test_tiddler_slash.py
test/test_tiddlers_fields.py
test/test_urlmap.py
test/test_user.py
test/test_validate.py
test/test_web.py
test/test_web_304_handling.py
test/test_web_bag.py
test/test_web_bag_tiddlers.py
test/test_web_bags.py
test/test_web_challenge.py
test/test_web_extract.py
test/test_web_http_api.py
test/test_web_json_tiddler.py
test/test_web_negotiate.py
test/test_web_recipe.py
tiddlyweb.egg-info/PKG-INFO
tiddlyweb.egg-info/SOURCES.txt
tiddlyweb.egg-info/dependency_links.txt
tiddlyweb.egg-info/not-zip-safe
tiddlyweb.egg-info/requires.txt
tiddlyweb.egg-info/top_level.txt
