Metadata-Version: 1.1
Name: tiddlyweb
Version: 2.4.2
Summary: An optionally headless, extensible HTTP datastore for tiddlers: bits of stuff.
Home-page: http://pypi.python.org/pypi/tiddlyweb
Author: Chris Dent
Author-email: cdent@peermore.com
License: UNKNOWN
Platform: Posix; MacOS X; Windows
Classifier: Environment :: Web Environment
Classifier: License :: OSI Approved :: BSD License
Classifier: Operating System :: OS Independent
Classifier: Programming Language :: Python :: 2.6
Classifier: Programming Language :: Python :: 2.7
Classifier: Programming Language :: Python :: 3.3
Classifier: Topic :: Internet :: WWW/HTTP :: WSGI :: Application
